{
    "banks": {
        "45": [
            {
                "sum": "800000.0",
                "sum_comment": "",
                "sum_foreign": "0",
                "sum_foreign_comment": "",
                "sum_foreign_units": "\u0433\u0440\u043d",
                "sum_units": "\u0433\u0440\u043d"
            }
        ],
        "46": [
            {
                "sum": "0",
                "sum_comment": "",
                "sum_foreign": "0",
                "sum_foreign_comment": "",
                "sum_foreign_units": "\u0433\u0440\u043d",
                "sum_units": "\u0433\u0440\u043d"
            }
        ],
        "47": [
            {
                "sum": "0",
                "sum_comment": "",
                "sum_foreign": "0",
                "sum_foreign_comment": "",
                "sum_foreign_units": "\u0433\u0440\u043d",
                "sum_units": "\u0433\u0440\u043d"
            }
        ],
        "48": [
            {
                "sum": "0",
                "sum_comment": "",
                "sum_foreign": "0",
                "sum_foreign_comment": "",
                "sum_foreign_units": "\u0433\u0440\u043d",
                "sum_units": "\u0433\u0440\u043d"
            }
        ],
        "49": [
            {
                "sum": "0",
                "sum_comment": "",
                "sum_foreign": "0",
                "sum_foreign_comment": "",
                "sum_foreign_units": "\u0433\u0440\u043d",
                "sum_units": "\u0433\u0440\u043d"
            }
        ],
        "50": [
            {
                "sum": "0",
                "sum_comment": "",
                "sum_foreign": "0",
                "sum_foreign_comment": "",
                "sum_foreign_units": "\u0433\u0440\u043d",
                "sum_units": "\u0433\u0440\u043d"
            }
        ],
        "51": [
            {
                "sum": "950000.0",
                "sum_comment": "",
                "sum_foreign": "0",
                "sum_foreign_comment": "",
                "sum_foreign_units": "\u0433\u0440\u043d",
                "sum_units": "\u0433\u0440\u043d"
            }
        ],
        "52": [
            {
                "sum": "0",
                "sum_comment": "",
                "sum_foreign": "0",
                "sum_foreign_comment": "",
                "sum_foreign_units": "\u0433\u0440\u043d",
                "sum_units": "\u0433\u0440\u043d"
            }
        ],
        "53": [
            {
                "sum": "0",
                "sum_comment": "",
                "sum_foreign": "0",
                "sum_foreign_comment": "",
                "sum_foreign_units": "\u0433\u0440\u043d",
                "sum_units": "\u0433\u0440\u043d"
            }
        ]
    },
    "declaration": {
        "needs_scancopy_check": "",
        "notfull": "",
        "notfull_lostpages": "",
        "source": "CHESNO",
        "url": "http://gapp.rada.gov.ua/declview/Home/Main/2281/2013"
    },
    "estate": {
        "25": [
            {
                "address": "",
                "costs": "",
                "costs_comment": "",
                "costs_rent": "",
                "costs_rent_comment": "",
                "location_raw": "",
                "region": "",
                "space": "56.46",
                "space_comment": "",
                "space_units": ""
            }
        ],
        "27": [
            {
                "address": "",
                "costs": "",
                "costs_comment": "",
                "costs_rent": "1000",
                "costs_rent_comment": "",
                "location_raw": "",
                "region": "",
                "space": "24.0",
                "space_comment": "",
                "space_units": ""
            }
        ],
        "28": [
            {
                "address": "",
                "costs": "",
                "costs_comment": "",
                "costs_rent": "60000",
                "costs_rent_comment": "",
                "location_raw": "\u043e\u0440\u0435\u043d\u0434\u0430",
                "region": "",
                "space": "126.0",
                "space_comment": "",
                "space_units": ""
            }
        ],
        "29": [
            {
                "address": "",
                "costs_property": "",
                "costs_property_comment": "",
                "costs_rent": "",
                "costs_rent_comment": "",
                "location_raw": "",
                "region": "",
                "space": "1500.0",
                "space_comment": "",
                "space_units": ""
            }
        ],
        "30": [
            {
                "address": "",
                "costs_property": "",
                "costs_property_comment": "",
                "costs_rent": "",
                "costs_rent_comment": "",
                "location_raw": "",
                "region": "",
                "space": "120.0",
                "space_comment": "",
                "space_units": ""
            }
        ],
        "31": [
            {
                "address": "",
                "costs_property": "",
                "costs_property_comment": "",
                "costs_rent": "",
                "costs_rent_comment": "",
                "location_raw": "",
                "region": "",
                "space": "100.0",
                "space_comment": "",
                "space_units": ""
            },
            {
                "address": "",
                "costs_property": "",
                "costs_property_comment": "",
                "costs_rent": "",
                "costs_rent_comment": "",
                "location_raw": "",
                "region": "",
                "space": "56.46",
                "space_comment": "",
                "space_units": ""
            }
        ],
        "33": [
            {
                "address": "",
                "costs_property": "",
                "costs_property_comment": "",
                "costs_rent": "",
                "costs_rent_comment": "",
                "location_raw": "",
                "region": "",
                "space": "30.0",
                "space_comment": "",
                "space_units": ""
            }
        ],
        "34": [
            {
                "address": "",
                "costs_property": "",
                "costs_property_comment": "",
                "costs_rent": "",
                "costs_rent_comment": "",
                "location_raw": "",
                "region": "",
                "space": "2717.0",
                "space_comment": "",
                "space_units": ""
            }
        ]
    },
    "ft_src": "Mercedes-Benz 500 5000\n2012\n\u0417\u0410\u0417 965 887 \u043a\u0443\u0431.\u0441\u043c, 19 \u043a\u0412\u0442\n1965\nLexus 350 3500 \u043a\u0443\u0431.\u0441\u043c, 233 \u043a\u0412\u0442\n2010\n\u0420\u0438\u0431\u0430\u043a\n\u0414\u0435\u043f\u0443\u0442\u0430\u0442 7-\u0433\u043e \u0441\u043a\u043b\u0438\u043a\u0430\u043d\u043d\u044f\n\u0412\u0430\u0441\u0438\u043b\u044c\u043e\u0432\u0438\u0447\n\u0420\u0438\u0431\u0430\u043a \u0412\u043e\u043b\u043e\u0434\u0438\u043c\u0438\u0440 \u0412\u0430\u0441\u0438\u043b\u044c\u043e\u0432\u0438\u0447\n\u0414\u0435\u043f\u0443\u0442\u0430\u0442 7-\u0433\u043e \u0441\u043a\u043b\u0438\u043a\u0430\u043d\u043d\u044f\n\u0417\u0430\u0433\u0430\u043b\u044c\u043d\u043e\u0434\u0435\u0440\u0436\u0430\u0432\u043d\u0438\u0439 \u0440\u0435\u0433\u0456\u043e\u043d\n\u0412\u0435\u0440\u0445\u043e\u0432\u043d\u0430 \u0440\u0430\u0434\u0430 \u0423\u043a\u0440\u0430\u0457\u043d\u0438\n\u0420\u0438\u0431\u0430\u043a \u0412\u043e\u043b\u043e\u0434\u0438\u043c\u0438\u0440 \u0412\u0430\u0441\u0438\u043b\u044c\u043e\u0432\u0438\u0447\n\u0412\u043e\u043b\u043e\u0434\u0438\u043c\u0438\u0440 \u0412\u0430\u0441\u0438\u043b\u044c\u043e\u0432\u0438\u0447 \u0420\u0438\u0431\u0430\u043a\n\u0412\u043e\u043b\u043e\u0434\u0438\u043c\u0438\u0440 \u0420\u0438\u0431\u0430\u043a\n\u0414\u0440\u0443\u0436\u0438\u043d\u0430\n\u0420\u0438\u0431\u0430\u043a \u0410.\u0406.\n\u0412\u043e\u043b\u043e\u0434\u0438\u043c\u0438\u0440\n950000.0\n800000.0\n30.0\n2717.0\n1500.0\n126.0\n\u043e\u0440\u0435\u043d\u0434\u0430\n60000\n120.0\n24.0\n1000\n56.46\n100.0\n56.46\n207034.0\n465317.0\n255111.0\n47502.0\n110000.0\n140000.0\n3066506.0\n612625.0\n3719325.0\n40480.0\n160000.0\n55000.0\n55000.0\n160000.0\n3066506.0\n140000.0\n110000.0\n40480.0\n465317.0\n207034.0\n3719325.0\n612625.0\n47502.0\n255111.0\n1965\n\u0417\u0410\u0417 965 887 \u043a\u0443\u0431.\u0441\u043c, 19 \u043a\u0412\u0442\n2010\nLexus 350 3500 \u043a\u0443\u0431.\u0441\u043c, 233 \u043a\u0412\u0442\n2012\nMercedes-Benz 500 5000\n1965\n\u0417\u0410\u0417 965 887 \u043a\u0443\u0431.\u0441\u043c, 19 \u043a\u0412\u0442\n2010\nLexus 350 3500 \u043a\u0443\u0431.\u0441\u043c, 233 \u043a\u0412\u0442\n2012\nMercedes-Benz 500 5000\n1000\n24.0\n30.0\n\u043e\u0440\u0435\u043d\u0434\u0430\n60000\n126.0\n1500.0\n100.0\n56.46\n120.0\n2717.0\n56.46\n950000.0\n800000.0\n47502.0\n255111.0\n140000.0\n110000.0\n40480.0\n3719325.0\n612625.0\n3066506.0\n465317.0\n207034.0\n\u0417\u0410\u0417 965 887 \u043a\u0443\u0431.\u0441\u043c, 19 \u043a\u0412\u0442\n1965\nLexus 350 3500 \u043a\u0443\u0431.\u0441\u043c, 233 \u043a\u0412\u0442\n2010\nMercedes-Benz 500 5000\n2012\n\u0414\u0435\u043f\u0443\u0442\u0430\u0442 7-\u0433\u043e \u0441\u043a\u043b\u0438\u043a\u0430\u043d\u043d\u044f\n\u0420\u0438\u0431\u0430\u043a\n\u0420\u0438\u0431\u0430\u043a \u0412\u043e\u043b\u043e\u0434\u0438\u043c\u0438\u0440 \u0412\u0430\u0441\u0438\u043b\u044c\u043e\u0432\u0438\u0447\n\u0412\u043e\u043b\u043e\u0434\u0438\u043c\u0438\u0440 \u0412\u0430\u0441\u0438\u043b\u044c\u043e\u0432\u0438\u0447 \u0420\u0438\u0431\u0430\u043a\n\u0412\u043e\u043b\u043e\u0434\u0438\u043c\u0438\u0440 \u0420\u0438\u0431\u0430\u043a\n\u0420\u0438\u0431\u0430\u043a \u0412\u043e\u043b\u043e\u0434\u0438\u043c\u0438\u0440 \u0412\u0430\u0441\u0438\u043b\u044c\u043e\u0432\u0438\u0447\n\u0420\u0438\u0431\u0430\u043a \u0410.\u0406.\n\u0414\u0440\u0443\u0436\u0438\u043d\u0430\n\u0420\u0438\u0431\u0430\u043a \u0412\u043e\u043b\u043e\u0434\u0438\u043c\u0438\u0440 \u0412\u0430\u0441\u0438\u043b\u044c\u043e\u0432\u0438\u0447\n\u0417\u0430\u0433\u0430\u043b\u044c\u043d\u043e\u0434\u0435\u0440\u0436\u0430\u0432\u043d\u0438\u0439 \u0440\u0435\u0433\u0456\u043e\u043d\n\u0414\u0435\u043f\u0443\u0442\u0430\u0442 7-\u0433\u043e \u0441\u043a\u043b\u0438\u043a\u0430\u043d\u043d\u044f\n\u0412\u0435\u0440\u0445\u043e\u0432\u043d\u0430 \u0440\u0430\u0434\u0430 \u0423\u043a\u0440\u0430\u0457\u043d\u0438\n\u0412\u0430\u0441\u0438\u043b\u044c\u043e\u0432\u0438\u0447\n\u0412\u043e\u043b\u043e\u0434\u0438\u043c\u0438\u0440\n160000.0\n55000.0\n255111.0\n47502.0\n207034.0\n465317.0\n612625.0\n3719325.0\n110000.0\n140000.0\n40480.0\n3066506.0\n1000\n24.0\n120.0\n\u043e\u0440\u0435\u043d\u0434\u0430\n60000\n126.0\n56.46\n1500.0\n30.0\n100.0\n56.46\n2717.0\n800000.0\n950000.0\n160000.0\n55000.0\n\u0420\u0438\u0431\u0430\u043a \u0410.\u0406.\n\u0414\u0440\u0443\u0436\u0438\u043d\u0430\n\u0420\u0438\u0431\u0430\u043a \u0412\u043e\u043b\u043e\u0434\u0438\u043c\u0438\u0440 \u0412\u0430\u0441\u0438\u043b\u044c\u043e\u0432\u0438\u0447\n\u0412\u043e\u043b\u043e\u0434\u0438\u043c\u0438\u0440 \u0412\u0430\u0441\u0438\u043b\u044c\u043e\u0432\u0438\u0447 \u0420\u0438\u0431\u0430\u043a\n\u0412\u043e\u043b\u043e\u0434\u0438\u043c\u0438\u0440 \u0420\u0438\u0431\u0430\u043a\n\u0420\u0438\u0431\u0430\u043a \u0412\u043e\u043b\u043e\u0434\u0438\u043c\u0438\u0440 \u0412\u0430\u0441\u0438\u043b\u044c\u043e\u0432\u0438\u0447\n\u0412\u0430\u0441\u0438\u043b\u044c\u043e\u0432\u0438\u0447\n\u0420\u0438\u0431\u0430\u043a\n\u0412\u043e\u043b\u043e\u0434\u0438\u043c\u0438\u0440\n\u0414\u0435\u043f\u0443\u0442\u0430\u0442 7-\u0433\u043e \u0441\u043a\u043b\u0438\u043a\u0430\u043d\u043d\u044f\n\u0414\u0435\u043f\u0443\u0442\u0430\u0442 7-\u0433\u043e \u0441\u043a\u043b\u0438\u043a\u0430\u043d\u043d\u044f\n\u0417\u0430\u0433\u0430\u043b\u044c\u043d\u043e\u0434\u0435\u0440\u0436\u0430\u0432\u043d\u0438\u0439 \u0440\u0435\u0433\u0456\u043e\u043d\n\u0412\u0435\u0440\u0445\u043e\u0432\u043d\u0430 \u0440\u0430\u0434\u0430 \u0423\u043a\u0440\u0430\u0457\u043d\u0438\n\u0420\u0438\u0431\u0430\u043a \u0412\u043e\u043b\u043e\u0434\u0438\u043c\u0438\u0440 \u0412\u0430\u0441\u0438\u043b\u044c\u043e\u0432\u0438\u0447\n100.0\n56.46\n56.46\n\u043e\u0440\u0435\u043d\u0434\u0430\n60000\n126.0\n1000\n24.0\n120.0\n30.0\n2717.0\n1500.0\n\u0414\u0435\u043f\u0443\u0442\u0430\u0442 7-\u0433\u043e \u0441\u043a\u043b\u0438\u043a\u0430\u043d\u043d\u044f\n\u0417\u0430\u0433\u0430\u043b\u044c\u043d\u043e\u0434\u0435\u0440\u0436\u0430\u0432\u043d\u0438\u0439 \u0440\u0435\u0433\u0456\u043e\u043d\n\u0412\u0435\u0440\u0445\u043e\u0432\u043d\u0430 \u0440\u0430\u0434\u0430 \u0423\u043a\u0440\u0430\u0457\u043d\u0438\n\u0414\u0435\u043f\u0443\u0442\u0430\u0442 7-\u0433\u043e \u0441\u043a\u043b\u0438\u043a\u0430\u043d\u043d\u044f\n\u0412\u043e\u043b\u043e\u0434\u0438\u043c\u0438\u0440\n\u0420\u0438\u0431\u0430\u043a \u0410.\u0406.\n\u0414\u0440\u0443\u0436\u0438\u043d\u0430\n\u0412\u0430\u0441\u0438\u043b\u044c\u043e\u0432\u0438\u0447\n\u0420\u0438\u0431\u0430\u043a\n\u0420\u0438\u0431\u0430\u043a \u0412\u043e\u043b\u043e\u0434\u0438\u043c\u0438\u0440 \u0412\u0430\u0441\u0438\u043b\u044c\u043e\u0432\u0438\u0447\n\u0420\u0438\u0431\u0430\u043a \u0412\u043e\u043b\u043e\u0434\u0438\u043c\u0438\u0440 \u0412\u0430\u0441\u0438\u043b\u044c\u043e\u0432\u0438\u0447\n\u0412\u043e\u043b\u043e\u0434\u0438\u043c\u0438\u0440 \u0412\u0430\u0441\u0438\u043b\u044c\u043e\u0432\u0438\u0447 \u0420\u0438\u0431\u0430\u043a\n\u0412\u043e\u043b\u043e\u0434\u0438\u043c\u0438\u0440 \u0420\u0438\u0431\u0430\u043a\n\u0420\u0438\u0431\u0430\u043a \u0412\u043e\u043b\u043e\u0434\u0438\u043c\u0438\u0440 \u0412\u0430\u0441\u0438\u043b\u044c\u043e\u0432\u0438\u0447\n800000.0\n950000.0",
    "general": {
        "addresses_raw": "",
        "addresses_raw_hidden": "",
        "family": [
            {
                "family_name": "\u0420\u0438\u0431\u0430\u043a \u0410.\u0406.",
                "relations": "\u0414\u0440\u0443\u0436\u0438\u043d\u0430"
            }
        ],
        "family_raw": "",
        "full_name": "\u0420\u0438\u0431\u0430\u043a \u0412\u043e\u043b\u043e\u0434\u0438\u043c\u0438\u0440 \u0412\u0430\u0441\u0438\u043b\u044c\u043e\u0432\u0438\u0447",
        "full_name_for_sorting": "\u0420\u0418\u0411\u0410\u041a \u0412\u041e\u041b\u041e\u0414\u0418\u041c\u0418\u0420 \u0412\u0410\u0421\u0418\u041b\u042c\u041e\u0412\u0418\u0427",
        "full_name_suggest": {
            "input": [
                "\u0420\u0438\u0431\u0430\u043a \u0412\u043e\u043b\u043e\u0434\u0438\u043c\u0438\u0440 \u0412\u0430\u0441\u0438\u043b\u044c\u043e\u0432\u0438\u0447",
                "\u0412\u043e\u043b\u043e\u0434\u0438\u043c\u0438\u0440 \u0412\u0430\u0441\u0438\u043b\u044c\u043e\u0432\u0438\u0447 \u0420\u0438\u0431\u0430\u043a",
                "\u0412\u043e\u043b\u043e\u0434\u0438\u043c\u0438\u0440 \u0420\u0438\u0431\u0430\u043a"
            ]
        },
        "inn": "",
        "last_name": "\u0420\u0438\u0431\u0430\u043a",
        "last_name_hidden": "",
        "last_name_unclear": "",
        "name": "\u0412\u043e\u043b\u043e\u0434\u0438\u043c\u0438\u0440",
        "name_hidden": "",
        "name_unclear": "",
        "patronymic": "\u0412\u0430\u0441\u0438\u043b\u044c\u043e\u0432\u0438\u0447",
        "patronymic_hidden": "",
        "patronymic_unclear": "",
        "post": {
            "office": "\u0412\u0435\u0440\u0445\u043e\u0432\u043d\u0430 \u0440\u0430\u0434\u0430 \u0423\u043a\u0440\u0430\u0457\u043d\u0438",
            "post": "\u0414\u0435\u043f\u0443\u0442\u0430\u0442 7-\u0433\u043e \u0441\u043a\u043b\u0438\u043a\u0430\u043d\u043d\u044f",
            "region": "\u0417\u0430\u0433\u0430\u043b\u044c\u043d\u043e\u0434\u0435\u0440\u0436\u0430\u0432\u043d\u0438\u0439 \u0440\u0435\u0433\u0456\u043e\u043d"
        },
        "post_raw": "\u0414\u0435\u043f\u0443\u0442\u0430\u0442 7-\u0433\u043e \u0441\u043a\u043b\u0438\u043a\u0430\u043d\u043d\u044f"
    },
    "id": "chesno_1860",
    "income": {
        "10": {
            "comment": "",
            "family": "",
            "family_comment": "",
            "value": "40480.0"
        },
        "11": {
            "comment": "",
            "family": "",
            "family_comment": "",
            "value": ""
        },
        "12": {
            "comment": "",
            "family": "",
            "family_comment": "",
            "value": ""
        },
        "13": {
            "comment": "",
            "family": "",
            "family_comment": "",
            "value": ""
        },
        "14": {
            "comment": "",
            "family": "",
            "family_comment": "",
            "value": ""
        },
        "15": {
            "comment": "",
            "family": "",
            "family_comment": "",
            "value": ""
        },
        "16": {
            "comment": "",
            "family": "",
            "family_comment": "",
            "value": ""
        },
        "17": {
            "comment": "",
            "family": "",
            "family_comment": "",
            "value": ""
        },
        "18": {
            "comment": "",
            "family": "",
            "family_comment": "",
            "value": ""
        },
        "19": {
            "comment": "",
            "family": "3066506.0",
            "family_comment": "",
            "value": ""
        },
        "20": {
            "comment": "",
            "family": "465317.0",
            "family_comment": "",
            "value": "207034.0"
        },
        "5": {
            "comment": "",
            "family": "3719325.0",
            "family_comment": "",
            "value": "612625.0"
        },
        "6": {
            "comment": "",
            "family": "47502.0",
            "family_comment": "",
            "value": "255111.0"
        },
        "7": {
            "comment": "",
            "family": "",
            "family_comment": "",
            "source_name": "",
            "value": ""
        },
        "8": {
            "comment": "",
            "family": "",
            "family_comment": "",
            "value": ""
        },
        "9": {
            "comment": "",
            "family": "140000.0",
            "family_comment": "",
            "value": "110000.0"
        }
    },
    "index_card": "\u0420\u0438\u0431\u0430\u043a \u0412\u043e\u043b\u043e\u0434\u0438\u043c\u0438\u0440 \u0412\u0430\u0441\u0438\u043b\u044c\u043e\u0432\u0438\u0447 \u0420\u0438\u0431\u0430\u043a \u0412\u043e\u043b\u043e\u0434\u0438\u043c\u0438\u0440 \u0412\u0430\u0441\u0438\u043b\u044c\u043e\u0432\u0438\u0447 \u0414\u0435\u043f\u0443\u0442\u0430\u0442 7-\u0433\u043e \u0441\u043a\u043b\u0438\u043a\u0430\u043d\u043d\u044f \u0412\u0435\u0440\u0445\u043e\u0432\u043d\u0430 \u0440\u0430\u0434\u0430 \u0423\u043a\u0440\u0430\u0457\u043d\u0438 \u0417\u0430\u0433\u0430\u043b\u044c\u043d\u043e\u0434\u0435\u0440\u0436\u0430\u0432\u043d\u0438\u0439 \u0440\u0435\u0433\u0456\u043e\u043d 2013 CHESNO http://gapp.rada.gov.ua/declview/Home/Main/2281/2013",
    "intro": {
        "declaration_year": 2013,
        "isnotdeclaration": ""
    },
    "liabilities": {
        "54": {
            "sum": "0",
            "sum_comment": "",
            "sum_foreign": "0",
            "sum_foreign_comment": ""
        },
        "55": {
            "sum": "0",
            "sum_comment": "",
            "sum_foreign": "0",
            "sum_foreign_comment": ""
        },
        "56": {
            "sum": "160000.0",
            "sum_comment": "",
            "sum_foreign": "0",
            "sum_foreign_comment": ""
        },
        "57": {
            "sum": "0",
            "sum_comment": "",
            "sum_foreign": "0",
            "sum_foreign_comment": ""
        },
        "58": {
            "sum": "0",
            "sum_comment": "",
            "sum_foreign": "0",
            "sum_foreign_comment": ""
        },
        "59": {
            "sum": "0",
            "sum_comment": "",
            "sum_foreign": "0",
            "sum_foreign_comment": ""
        },
        "60": {
            "sum": "0",
            "sum_comment": "",
            "sum_foreign": "0",
            "sum_foreign_comment": ""
        },
        "61": {
            "sum": "0",
            "sum_comment": "",
            "sum_foreign": "0",
            "sum_foreign_comment": ""
        },
        "62": {
            "sum": "55000.0",
            "sum_comment": "",
            "sum_foreign": "0",
            "sum_foreign_comment": ""
        },
        "63": {
            "sum": "0",
            "sum_comment": "",
            "sum_foreign": "0",
            "sum_foreign_comment": ""
        },
        "64": {
            "sum": "0",
            "sum_comment": "",
            "sum_foreign": "0",
            "sum_foreign_comment": ""
        }
    },
    "vehicle": {
        "35": [
            {
                "brand": "\u0417\u0410\u0417 965 887 \u043a\u0443\u0431.\u0441\u043c, 19 \u043a\u0412\u0442",
                "brand_hidden": "",
                "brand_info": "",
                "sum": "",
                "sum_comment": "",
                "sum_rent": "",
                "sum_rent_comment": "",
                "year": "1965"
            },
            {
                "brand": "Lexus 350 3500 \u043a\u0443\u0431.\u0441\u043c, 233 \u043a\u0412\u0442",
                "brand_hidden": "",
                "brand_info": "",
                "sum": "",
                "sum_comment": "",
                "sum_rent": "",
                "sum_rent_comment": "",
                "year": "2010"
            }
        ],
        "40": [
            {
                "brand": "Mercedes-Benz 500 5000",
                "brand_hidden": "",
                "brand_info": "",
                "sum": "",
                "sum_comment": "",
                "sum_rent": "",
                "sum_rent_comment": "",
                "year": "2012"
            }
        ]
    }
}